airflow_ai_sdk/__init__.py
airflow_ai_sdk/decorators/agent.py
airflow_ai_sdk/decorators/branch.py
airflow_ai_sdk/decorators/llm.py
airflow_ai_sdk/models/base.py
airflow_ai_sdk/models/tool.py
airflow_ai_sdk/operators/agent.py
airflow_ai_sdk/operators/llm.py
airflow_ai_sdk/operators/llm_branch.py
airflow_ai_sdk_slim-0.1.0a5.dist-info/METADATA
airflow_ai_sdk_slim-0.1.0a5.dist-info/WHEEL
airflow_ai_sdk_slim-0.1.0a5.dist-info/entry_points.txt
airflow_ai_sdk_slim-0.1.0a5.dist-info/RECORD
